tf_core/__init__.py
tf_core/bootstrap.py
tf_core/frameconnection.py
tf_core/httpclient.py
tf_core/modulemanager.py
tf_core/paths.py
tf_core/router.py
tf_core/modules/BaseFrameModule.py
tf_core/modules/FrameModule.py
tf_core/modules/__init__.py
tf_core/web/__init__.py
tf_core/web/webserver.py
thoughtframe_python-0.1.0.dist-info/licenses/LICENSE
thoughtframe_python-0.1.0.dist-info/METADATA
thoughtframe_python-0.1.0.dist-info/WHEEL
thoughtframe_python-0.1.0.dist-info/top_level.txt
thoughtframe_python-0.1.0.dist-info/RECORD
