Metadata-Version: 2.4
Name: thoughtframe-python
Version: 0.1.0
Summary: Reference Python runtime for ThoughtFrame
Author: Ian Miller
License: Apache License
Requires-Python: >=3.10
License-File: LICENSE
Requires-Dist: aiohttp
Requires-Dist: websockets
Dynamic: license-file
